configutils/__init__.py
configutils/parser.py
configutils/utils.py
serval_config_utils-0.1.4.dist-info/LICENSE
serval_config_utils-0.1.4.dist-info/WHEEL
serval_config_utils-0.1.4.dist-info/METADATA
serval_config_utils-0.1.4.dist-info/RECORD
