Metadata-Version: 2.1
Name: serval-config-utils
Version: 0.1.4
Summary: SerVal-Config-Utils automatically parse configurations from multiple sources into a single python dictionary.
License: MIT
Author: Thibault Simonetto
Author-email: thibault.simonetto@uni.lu
Requires-Python: >=3.6.2,<4.0.0
Classifier: License :: OSI Approved :: MIT License
Classifier: Programming Language :: Python :: 3
Classifier: Programming Language :: Python :: 3.10
Classifier: Programming Language :: Python :: 3.7
Classifier: Programming Language :: Python :: 3.8
Classifier: Programming Language :: Python :: 3.9
Requires-Dist: PyYAML (>=5.1,<7.0)
Requires-Dist: mergedeep (>=1.3.4,<2.0.0)
